adminvisualsortable/__init__.py
adminvisualsortable/admin.py
adminvisualsortable/apps.py
adminvisualsortable/models.py
adminvisualsortable/tests.py
adminvisualsortable/urls.py
adminvisualsortable/views.py
adminvisualsortable/migrations/__init__.py
adminvisualsortable/static/adminvisualsortable/css/adminvisualsortable.css
adminvisualsortable/static/adminvisualsortable/css/all.mini.css
adminvisualsortable/static/adminvisualsortable/css/yui/cssreset-min.css
adminvisualsortable/static/adminvisualsortable/img/placeholder-image.png
adminvisualsortable/static/adminvisualsortable/js/Sortable.min.js
adminvisualsortable/static/adminvisualsortable/js/admin-sorter.js
adminvisualsortable/static/adminvisualsortable/js/modernizr-custom-only-webp.js
adminvisualsortable/templates/change_form.html
adminvisualsortable/templates/change_list.html
adminvisualsortable/templates/tabbed_change_form.html
adminvisualsortable/templates/adminvisualsortable/sort-base.html
adminvisualsortable/templates/adminvisualsortable/sort-inline-models.html
adminvisualsortable/templates/adminvisualsortable/sort-models-pivot.html
adminvisualsortable/templates/adminvisualsortable/sort-models.html
adminvisualsortable/templatetags/__init__.py
adminvisualsortable/templatetags/admin_utils.py
django_adminvisualsortable-2.5.0.dist-info/METADATA
django_adminvisualsortable-2.5.0.dist-info/WHEEL
django_adminvisualsortable-2.5.0.dist-info/top_level.txt
django_adminvisualsortable-2.5.0.dist-info/RECORD
